{
  "lang": "node",
  "projects": [
    {
      "name": "axios",
      "branch": "main",
      "url": "https://github.com/axios/axios"
    },
    {
      "name": "koa",
      "branch": "master",
      "url": "https://github.com/koajs/koa"
    },
    {
      "name": "express",
      "branch": "master",
      "url": "https://github.com/expressjs/express"
    },
    {
      "name": "nodejs",
      "branch": "main",
      "url": "https://github.com/nodejs/node"
    },
    {
      "name": "npm",
      "branch": "latest",
      "url": "https://github.com/npm/cli"
    }
  ]
}
